README.md
setup.py
aws_mfa_tool/__init__.py
aws_mfa_tool/cli.py
aws_mfa_tool.egg-info/PKG-INFO
aws_mfa_tool.egg-info/SOURCES.txt
aws_mfa_tool.egg-info/dependency_links.txt
aws_mfa_tool.egg-info/entry_points.txt
aws_mfa_tool.egg-info/requires.txt
aws_mfa_tool.egg-info/top_level.txt