Metadata-Version: 1.0
Name: aws-mfa-tool
Version: 0.1.2
Summary: Simple CLI for caching temporary credentials in ~/.aws/credentials
Home-page: UNKNOWN
Author: UNKNOWN
Author-email: UNKNOWN
License: UNKNOWN
Platform: UNKNOWN
